WorkspaceAutomation/__errors__.py
WorkspaceAutomation/__init__.py
WorkspaceAutomation/__main__.py
WorkspaceAutomation/__vars__.py
WorkspaceAutomation/app.py
WorkspaceAutomation/common.py
WorkspaceAutomation/set_up.py
WorkspaceAutomation/Config/__init__.py
WorkspaceAutomation/Config/functions.py
WorkspaceAutomation/WorkspaceManager/__init__.py
WorkspaceAutomation/WorkspaceManager/functions.py
WorkspaceAutomation/WorkspaceManager/shared_menus.py
WorkspaceAutomation/WorkspaceManager/builders/Contents.py
WorkspaceAutomation/WorkspaceManager/builders/__init__.py
WorkspaceAutomation/WorkspaceManager/builders/github.py
WorkspaceAutomation/WorkspaceManager/runners/__init__.py
WorkspaceAutomation/WorkspaceManager/runners/apps.py
WorkspaceAutomation/WorkspaceManager/runners/webs.py
WorkspaceAutomation/resources/__init__.py
WorkSpaceAutomation-0.1.1.dist-info/LICENSE
WorkSpaceAutomation-0.1.1.dist-info/METADATA
WorkSpaceAutomation-0.1.1.dist-info/WHEEL
WorkSpaceAutomation-0.1.1.dist-info/entry_points.txt
WorkSpaceAutomation-0.1.1.dist-info/top_level.txt
WorkSpaceAutomation-0.1.1.dist-info/RECORD
