Metadata-Version: 2.1
Name: WorkSpaceAutomation
Version: 0.1.1
Summary: A project to help all fellow devs to not waste time in doing the boring and repetitive stuff
Author: Dtar380
License: GNU GENERAL PUBLIC LICENSE
Project-URL: Homepage, https://github.com/Dtar380/WorkspaceAutomation
Project-URL: Documentation, https://readthedocs.org
Project-URL: Repository, https://github.com/Dtar380/WorkspaceAutomation
Project-URL: Bug Tracker, https://github.com/Dtar380/WorkspaceAutomation/issues
Project-URL: Changelog, https://github.com/Dtar380/Workspace/blob/main/CHANGELOG.md
Classifier: Development Status :: 4 - Beta
Classifier: Intended Audience :: Developers
Classifier: Topic :: Utilities
Classifier: Topic :: Software Development
Classifier: License :: OSI Approved :: MIT License
Classifier: Programming Language :: Python :: 3.12
Requires-Python: >=3.12
License-File: LICENSE
Requires-Dist: python-dotenv==1.0.1
Requires-Dist: requests==2.32.3
Requires-Dist: click==8.1.7
Requires-Dist: yaspin==3.0.2
Requires-Dist: inquirer==3.3.0
Requires-Dist: cryptography==43.0.0
Provides-Extra: dev
Requires-Dist: setuptools==72.1.0; extra == "dev"
Requires-Dist: wheel==0.44.0; extra == "dev"
Requires-Dist: briefcase==0.3.19; extra == "dev"
Provides-Extra: test
Requires-Dist: pytest; extra == "test"
